LICENSE
MANIFEST.in
README.rst
setup.cfg
setup.py
docs/Makefile
docs/authors.rst
docs/conf.py
docs/contributing.rst
docs/history.rst
docs/index.rst
docs/installation.rst
docs/make.bat
docs/readme.rst
docs/usage.rst
lambdasim/__init__.py
lambdasim/config.py
lambdasim/conversions.py
lambdasim/dsp.py
lambdasim/filter.py
lambdasim/io.py
lambdasim/sim.py
lambdasim/snd.py
lambdasim/source.py
lambdasim/util.py
lambdasim.egg-info/PKG-INFO
lambdasim.egg-info/SOURCES.txt
lambdasim.egg-info/dependency_links.txt
lambdasim.egg-info/not-zip-safe
lambdasim.egg-info/top_level.txt
tests/__init__.py
tests/test_lambdasim.py