Metadata-Version: 1.1
Name: lambdasim
Version: 0.1.0
Summary: Python utilities to interact with Lambda (FDTD acoustic simulations)
Home-page: https://github.com/gesellkammer/lambdasim
Author: Eduardo Moguillansky
Author-email: eduardo.moguillansky@gmail.com
License: BSD
Keywords: lambdasim
Platform: UNKNOWN
Classifier: Development Status :: 2 - Pre-Alpha
Classifier: Intended Audience :: Developers
Classifier: License :: OSI Approved :: BSD License
Classifier: Natural Language :: English
Classifier: Programming Language :: Python :: 2.7
